pyroadd/__init__.py
pyroadd/pyro_add.py
pyroadd-0.1.2.dist-info/LICENSE
pyroadd-0.1.2.dist-info/METADATA
pyroadd-0.1.2.dist-info/WHEEL
pyroadd-0.1.2.dist-info/top_level.txt
pyroadd-0.1.2.dist-info/RECORD
